{
  "version": "1.0.0",
  "structure": {
    "src": [
      "__mocks__",
      "api",
      "assets",
      "cache",
      "components",
      "config",
      "context",
      "contracts",
      "data",
      "globe-engine",
      "...truncated"
    ],
    "scripts": [
      "deploy.ts",
      "mock-api-server.js",
      "onboard.cjs"
    ],
    "docs": [
      "Decentralized Web3 dApp Development Guide.markdown",
      "testing-policy.md"
    ],
    "public": [
      "borders.geojson",
      "starcom.ico",
      "starcom.png",
      "territories.geojson"
    ],
    "rust": [
      "fetch-test",
      "wasm-ephemeris",
      "wasm-mini-server"
    ]
  },
  "artifacts": [
    "web3-login-testing-plan.artifact",
    "web3-login-ux-flow.artifact",
    "web3-network-config.artifact",
    "web3-ui-components-v2.artifact",
    "web3-ui-testing-v2.artifact",
    "web3-ui-ux-flow-v2.artifact"
  ],
  "aiHints": {
    "mainAppDir": "src",
    "contractsDir": "src/contracts",
    "docsDir": "docs",
    "entryPoints": [
      "src/App.tsx",
      "src/main.tsx"
    ]
  },
  "generatedAt": "2025-06-14T15:14:54.721Z"
}